Metadata-Version: 1.0
Name: find-palindromes
Version: 1.0
Summary: Пакет для нахождения палиндромов чисел в заданном диапазоне, с помощью операций Перевернуть и сложить
Home-page: UNKNOWN
Author: Eugene Martyshov
Author-email: e.martyshov@yandex.ru
License: UNKNOWN
Platform: UNKNOWN
